[
[
  {
    "playlist_id": 5,
    "artist": "Beyonc\u00e9",
    "song": "Formation",
    "genre": "R&B"
  },
  {
    "playlist_id": 1,
    "artist": "The Weeknd",
    "song": "Blinding Lights",
    "genre": "R&B"
  },
  {
    "playlist_id": 4,
    "artist": "Bruno Mars",
    "song": "24K Magic",
    "genre": "R&B"
  },
  {
    "playlist_id": 6,
    "artist": "Rihanna",
    "song": "Work",
    "genre": "R&B"
  },
  {
    "playlist_id": 3,
    "artist": "Frank Ocean",
    "song": "Thinkin Bout You",
    "genre": "R&B"
  },
  {
    "playlist_id": 2,
    "artist": "Alicia Keys",
    "song": "If I Ain't Got You",
    "genre": "R&B"
  },
  {
    "playlist_id": 0,
    "artist": "Drake",
    "song": "Hotline Bling",
    "genre": "R&B"
  },
  {
    "playlist_id": 7,
    "artist": "John Legend",
    "song": "All of Me",
    "genre": "R&B"
  },
  {
    "playlist_id": 5,
    "artist": "Beyonc\u00e9",
    "song": "Drunk in Love",
    "genre": "R&B"
  },
  {
    "playlist_id": 1,
    "artist": "The Weeknd",
    "song": "Starboy",
    "genre": "R&B"
  },
  {
    "playlist_id": 4,
    "artist": "Bruno Mars",
    "song": "That's What I Like",
    "genre": "R&B"
  },
  {
    "playlist_id": 6,
    "artist": "Rihanna",
    "song": "Needed Me",
    "genre": "R&B"
  },
  {
    "playlist_id": 3,
    "artist": "Frank Ocean",
    "song": "Lost",
    "genre": "R&B"
  },
  {
    "playlist_id": 2,
    "artist": "Alicia Keys",
    "song": "Fallin'",
    "genre": "R&B"
  },
  {
    "playlist_id": 0,
    "artist": "Drake",
    "song": "One Dance",
    "genre": "R&B"
  },
  {
    "playlist_id": 7,
    "artist": "John Legend",
    "song": "Ordinary People",
    "genre": "R&B"
  },
  {
    "playlist_id": 5,
    "artist": "Beyonc\u00e9",
    "song": "Halo",
    "genre": "R&B"
  },
  {
    "playlist_id": 1,
    "artist": "The Weeknd",
    "song": "Can't Feel My Face",
    "genre": "R&B"
  },
  {
    "playlist_id": 4,
    "artist": "Bruno Mars",
    "song": "Locked Out of Heaven",
    "genre": "R&B"
  },
  {
    "playlist_id": 6,
    "artist": "Rihanna",
    "song": "Diamonds",
    "genre": "R&B"
  },
  {
    "playlist_id": 3,
    "artist": "Frank Ocean",
    "song": "Pink + White",
    "genre": "R&B"
  },
  {
    "playlist_id": 2,
    "artist": "Alicia Keys",
    "song": "No One",
    "genre": "R&B"
  },
  {
    "playlist_id": 0,
    "artist": "Drake",
    "song": "Started From the Bottom",
    "genre": "R&B"
  },
  {
    "playlist_id": 7,
    "artist": "John Legend",
    "song": "Love Me Now",
    "genre": "R&B"
  },
  {
    "playlist_id": 5,
    "artist": "Beyonc\u00e9",
    "song": "Love On Top",
    "genre": "R&B"
  },
  {
    "playlist_id": 1,
    "artist": "The Weeknd",
    "song": "Earned It",
    "genre": "R&B"
  },
  {
    "playlist_id": 4,
    "artist": "Bruno Mars",
    "song": "Treasure",
    "genre": "R&B"
  },
  {
    "playlist_id": 6,
    "artist": "Rihanna",
    "song": "We Found Love",
    "genre": "R&B"
  },
  {
    "playlist_id": 3,
    "artist": "Frank Ocean",
    "song": "Nights",
    "genre": "R&B"
  },
  {
    "playlist_id": 2,
    "artist": "Alicia Keys",
    "song": "Empire State of Mind (Part II) Broken Down",
    "genre": "R&B"
  },
  {
    "playlist_id": 0,
    "artist": "Drake",
    "song": "Hold On, We're Going Home",
    "genre": "R&B"
  },
  {
    "playlist_id": 7,
    "artist": "John Legend",
    "song": "All of Me",
    "genre": "R&B"
  },
  {
    "playlist_id": 5,
    "artist": "Beyonc\u00e9",
    "song": "Partition",
    "genre": "R&B"
  },
  {
    "playlist_id": 1,
    "artist": "The Weeknd",
    "song": "The Hills",
    "genre": "R&B"
  },
  {
    "playlist_id": 4,
    "artist": "Bruno Mars",
    "song": "Grenade",
    "genre": "R&B"
  },
  {
    "playlist_id": 6,
    "artist": "Rihanna",
    "song": "Stay",
    "genre": "R&B"
  },
  {
    "playlist_id": 3,
    "artist": "Frank Ocean",
    "song": "Ivy",
    "genre": "R&B"
  },
  {
    "playlist_id": 2,
    "artist": "Alicia Keys",
    "song": "Girl on Fire",
    "genre": "R&B"
  },
  {
    "playlist_id": 0,
    "artist": "Drake",
    "song": "Hold My Hand",
    "genre": "R&B"
  },
  {
    "playlist_id": 7,
    "artist": "John Legend",
    "song": "Green Light",
    "genre": "R&B"
  },
  {
    "playlist_id": 5,
    "artist": "Beyonc\u00e9",
    "song": "Crazy in Love",
    "genre": "R&B"
  },
  {
    "playlist_id": 1,
    "artist": "The Weeknd",
    "song": "Can't Feel My Face",
    "genre": "R&B"
  },
  {
    "playlist_id": 4,
    "artist": "Bruno Mars",
    "song": "Just the Way You Are",
    "genre": "R&B"
  },
  {
    "playlist_id": 6,
    "artist": "Rihanna",
    "song": "Love On The Brain",
    "genre": "R&B"
  },
  {
    "playlist_id": 3,
    "artist": "Frank Ocean",
    "song": "Self Control",
    "genre": "R&B"
  },
  {
    "playlist_id": 2,
    "artist": "Alicia Keys",
    "song": "Fallin'",
    "genre": "R&B"
  },
  {
    "playlist_id": 0,
    "artist": "Drake",
    "song": "Passionfruit",
    "genre": "R&B"
  },
  {
    "playlist_id": 7,
    "artist": "John Legend",
    "song": "Save Room",
    "genre": "R&B"
  },
  {
    "playlist_id": 5,
    "artist": "Beyonc\u00e9",
    "song": "Irreplaceable",
    "genre": "R&B"
  },
  {
    "playlist_id": 1,
    "artist": "The Weeknd",
    "song": "In The Night",
    "genre": "R&B"
  },
  {
    "playlist_id": 4,
    "artist": "Bruno Mars",
    "song": "Versace On The Floor",
    "genre": "R&B"
  },
  {
    "playlist_id": 6,
    "artist": "Rihanna",
    "song": "Only Girl (In The World)",
    "genre": "R&B"
  },
  {
    "playlist_id": 3,
    "artist": "Frank Ocean",
    "song": "Super Rich Kids",
    "genre": "R&B"
  },
  {
    "playlist_id": 2,
    "artist": "Alicia Keys",
    "song": "Empire State of Mind (Part II) Broken Down",
    "genre": "R&B"
  },
  {
    "playlist_id": 0,
    "artist": "Drake",
    "song": "Nice For What",
    "genre": "R&B"
  },
  {
    "playlist_id": 7,
    "artist": "John Legend",
    "song": "P.D.A. (We Just Don't Care)",
    "genre": "R&B"
  }
],

[
  {
    "artist": "The Weeknd",
    "genre": "R&B",
    "song_name": "Can't Feel My Face"
  },
  {
    "artist": "Drake",
    "genre": "R&B",
    "song_name": "Hotline Bling"
  },
  {
    "artist": "Beyoncé",
    "genre": "R&B",
    "song_name": "Formation"
  },
  {
    "artist": "Rihanna, Kanye West, Paul McCartney",
    "genre": "R&B",
    "song_name": "FourFiveSeconds"
  },
  {
    "artist": "Chris Brown, Tyga",
    "genre": "R&B",
    "song_name": "Ayo"
  },
  {
    "artist": "Fetty Wap",
    "genre": "R&B",
    "song_name": "Trap Queen"
  },
  {
    "artist": "Jeremih, YG",
    "genre": "R&B",
    "song_name": "Don't Tell 'Em"
  },
  {
    "artist": "Jidenna",
    "genre": "R&B",
    "song_name": "Classic Man"
  },
  {
    "artist": "Wiz Khalifa, Charlie Puth",
    "genre": "R&B",
    "song_name": "See You Again"
  },
  {
    "artist": "Ciara",
    "genre": "R&B",
    "song_name": "Dance Like We're Making Love"
  },
  {
    "artist": "Miguel",
    "genre": "R&B",
    "song_name": "Coffee"
  },
  {
    "artist": "Tinashe, Iggy Azalea",
    "genre": "R&B",
    "song_name": "All Hands On Deck (Remix)"
  },
  {
    "artist": "Usher, Juicy J",
    "genre": "R&B",
    "song_name": "I Don't Mind"
  },
  {
    "artist": "Kehlani",
    "genre": "R&B",
    "song_name": "The Way ft. Chance the Rapper"
  },
  {
    "artist": "Ty Dolla $ign, Charli XCX, Tinashe",
    "genre": "R&B",
    "song_name": "Drop That Kitty"
  },
  {
    "artist": "Ne-Yo, Juicy J",
    "genre": "R&B",
    "song_name": "She Knows"
  },
  {
    "artist": "Jazmine Sullivan",
    "genre": "R&B",
    "song_name": "Dumb ft. Meek Mill"
  },
  {
    "artist": "Alessia Cara",
    "genre": "R&B",
    "song_name": "Here"
  },
  {
    "artist": "Bryson Tiller",
    "genre": "R&B",
    "song_name": "Don't"
  },
  {
    "artist": "The Weeknd",
    "genre": "R&B",
    "song_name": "Earned It"
  },
  {
    "artist": "Rae Sremmurd",
    "genre": "R&B",
    "song_name": "Come Get Her"
  },
  {
    "artist": "Janet Jackson",
    "genre": "R&B",
    "song_name": "No Sleeep"
  },
  {
    "artist": "Jamie Foxx, Chris Brown",
    "genre": "R&B",
    "song_name": "You Changed Me"
  },
  {
    "artist": "R. City, Adam Levine",
    "genre": "R&B",
    "song_name": "Locked Away"
  },
  {
    "artist": "PARTYNEXTDOOR, Drake",
    "genre": "R&B",
    "song_name": "Come and See Me"
  },
  {
    "artist": "Trey Songz",
    "genre": "R&B",
    "song_name": "Slow Motion"
  },
  {
    "artist": "Nicki Minaj, Beyoncé",
    "genre": "R&B",
    "song_name": "Feeling Myself"
  },
  {
    "artist": "Trey Songz",
    "genre": "R&B",
    "song_name": "About You"
  },
  {
    "artist": "Zendaya",
    "genre": "R&B",
    "song_name": "Something New ft. Chris Brown"
  },
  {
    "artist": "Jidenna, Roman GianArthur",
    "genre": "R&B",
    "song_name": "Classic Man (Remix)"
  },
  {
    "artist": "Bryson Tiller",
    "genre": "R&B",
    "song_name": "Exchange"
  },
  {
    "artist": "Demi Lovato",
    "genre": "R&B",
    "song_name": "Cool for the Summer"
  },
  {
    "artist": "Macklemore & Ryan Lewis, Eric Nally, Melle Mel, Kool Moe Dee, Grandmaster Caz",
    "genre": "R&B",
    "song_name": "Downtown"
  },
  {
    "artist": "Ty Dolla $ign, Fetty Wap",
    "genre": "R&B",
    "song_name": "When I See Ya"
  },
  {
    "artist": "Kehlani",
    "genre": "R&B",
    "song_name": "You Should Be Here"
  },
  {
    "artist": "Sevyn Streeter",
    "genre": "R&B",
    "song_name": "Don't Kill the Fun ft. Chris Brown"
  },
  {
    "artist": "Trey Songz",
    "genre": "R&B",
    "song_name": "Blessed"
  },
  {
    "artist": "Tory Lanez",
    "genre": "R&B",
    "song_name": "Say It"
  },
  {
    "artist": "Big Sean, Jhené Aiko",
    "genre": "R&B",
    "song_name": "I Know"
  },
  {
    "artist": "Adele",
    "genre": "R&B",
    "song_name": "Hello"
  },
  {
    "artist": "Miguel",
    "genre": "R&B",
    "song_name": "Waves"
  },
  {
    "artist": "Rihanna",
    "genre": "R&B",
    "song_name": "Bitch Better Have My Money"
  },
  {
    "artist": "Tank, Chris Brown, Siya, Sage the Gemini",
    "genre": "R&B",
    "song_name": "B Day"
  },
  {
    "artist": "Alessia Cara",
    "genre": "R&B",
    "song_name": "Wild Things"
  },
  {
    "artist": "Fetty Wap, Remy Boyz",
    "genre": "R&B",
    "song_name": "679"
  },
  {
    "artist": "Jeremih",
    "genre": "R&B",
    "song_name": "Oui"
  },
  {
    "artist": "Usher, Rick Ross",
    "genre": "R&B",
    "song_name": "Good Kisser (Remix)"
  },
  {
    "artist": "Chris Brown, Tyga",
    "genre": "R&B",
    "song_name": "Bitches N Marijuana"
  },
  {
    "artist": "Janelle Monáe, Jidenna",
    "genre": "R&B",
    "song_name": "Yoga"
  },
  {
    "artist": "K. Michelle",
    "genre": "R&B",
    "song_name": "Love 'Em All"
  },
  {
    "artist": "Ariana Grande",
    "genre": "R&B",
    "song_name": "Focus"
  },
  {
    "artist": "Beyoncé",
    "genre": "R&B",
    "song_name": "Formation"
  },
  {
    "artist": "Rihanna",
    "genre": "R&B",
    "song_name": "Work ft. Drake"
  },
  {
    "artist": "Drake",
    "genre": "R&B",
    "song_name": "One Dance ft. WizKid, Kyla"
  },
  {
    "artist": "The Weeknd",
    "genre": "R&B",
    "song_name": "Starboy ft. Daft Punk"
  },
  {
    "artist": "DJ Khaled",
    "genre": "R&B",
    "song_name": "Do You Mind ft. Nicki Minaj, Chris Brown, August Alsina, Jeremih, Future, Rick Ross"
  },
  {
    "artist": "Alicia Keys",
    "genre": "R&B",
    "song_name": "In Common"
  },
  {
    "artist": "Frank Ocean",
    "genre": "R&B",
    "song_name": "Ivy"
  },
  {
    "artist": "Solange",
    "genre": "R&B",
    "song_name": "Cranes in the Sky"
  },
  {
    "artist": "Beyoncé",
    "genre": "R&B",
    "song_name": "Hold Up"
  },
  {
    "artist": "Usher",
    "genre": "R&B",
    "song_name": "No Limit ft. Young Thug"
  },
  {
    "artist": "PARTYNEXTDOOR",
    "genre": "R&B",
    "song_name": "Come and See Me ft. Drake"
  },
  {
    "artist": "Rihanna",
    "genre": "R&B",
    "song_name": "Needed Me"
  },
  {
    "artist": "Bruno Mars",
    "genre": "R&B",
    "song_name": "24K Magic"
  },
  {
    "artist": "Kanye West",
    "genre": "R&B",
    "song_name": "Famous"
  },
  {
    "artist": "Childish Gambino",
    "genre": "R&B",
    "song_name": "Redbone"
  },
  {
    "artist": "Bryson Tiller",
    "genre": "R&B",
    "song_name": "Exchange"
  },
  {
    "artist": "The Weeknd",
    "genre": "R&B",
    "song_name": "I Feel It Coming ft. Daft Punk"
  },
  {
    "artist": "Rae Sremmurd",
    "genre": "R&B",
    "song_name": "Black Beatles ft. Gucci Mane"
  },
  {
    "artist": "Tory Lanez",
    "genre": "R&B",
    "song_name": "Luv"
  },
  {
    "artist": "Zay Hilfigerrr & Zayion McCall",
    "genre": "R&B",
    "song_name": "Juju On That Beat (TZ Anthem)"
  },
  {
    "artist": "Mary J. Blige",
    "genre": "R&B",
    "song_name": "Thick of It"
  },
  {
    "artist": "Travis Scott",
    "genre": "R&B",
    "song_name": "Goosebumps ft. Kendrick Lamar"
  },
  {
    "artist": "Ariana Grande",
    "genre": "R&B",
    "song_name": "Side to Side ft. Nicki Minaj"
  },
  {
    "artist": "DJ Khaled",
    "genre": "R&B",
    "song_name": "I Got the Keys ft. Jay-Z, Future"
  },
  {
    "artist": "Tank",
    "genre": "R&B",
    "song_name": "Please Don't Go"
  },
  {
    "artist": "Maxwell",
    "genre": "R&B",
    "song_name": "Lake by the Ocean"
  },
  {
    "artist": "Bryson Tiller",
    "genre": "R&B",
    "song_name": "Don't"
  },
  {
    "artist": "Kehlani",
    "genre": "R&B",
    "song_name": "Gangsta"
  },
  {
    "artist": "John Legend",
    "genre": "R&B",
    "song_name": "Love Me Now"
  },
  {
    "artist": "D.R.A.M.",
    "genre": "R&B",
    "song_name": "Broccoli ft. Lil Yachty"
  },
  {
    "artist": "Rihanna",
    "genre": "R&B",
    "song_name": "Kiss It Better"
  },
  {
    "artist": "Kehlani",
    "genre": "R&B",
    "song_name": "Distraction"
  },
  {
    "artist": "Jeremih",
    "genre": "R&B",
    "song_name": "Oui"
  },
  {
    "artist": "Beyoncé",
    "genre": "R&B",
    "song_name": "Sorry"
  },
  {
    "artist": "Khalid",
    "genre": "R&B",
    "song_name": "Location"
  },
  {
    "artist": "Rihanna",
    "genre": "R&B",
    "song_name": "Sex with Me"
  },
  {
    "artist": "Chance the Rapper",
    "genre": "R&B",
    "song_name": "No Problem ft. Lil Wayne, 2 Chainz"
  },
  {
    "artist": "Dvsn",
    "genre": "R&B",
    "song_name": "Hallucinations"
  },
  {
    "artist": "Beyoncé",
    "genre": "R&B",
    "song_name": "Sorry"
  },
  {
    "artist": "PARTYNEXTDOOR",
    "genre": "R&B",
    "song_name": "Not Nice"
  },
  {
    "artist": "Miguel",
    "genre": "R&B",
    "song_name": "Come Through and Chill ft. J. Cole, Salaam Remi"
  },
  {
    "artist": "Tory Lanez",
    "genre": "R&B",
    "song_name": "Say It"
  },
  {
    "artist": "Usher",
    "genre": "R&B",
    "song_name": "Crash"
  },
  {
    "artist": "Beyoncé",
    "genre": "R&B",
    "song_name": "Hold Up"
  },
  {
    "artist": "Frank Ocean",
    "genre": "R&B",
    "song_name": "Nikes"
  },
  {
    "artist": "Bryson Tiller",
    "genre": "R&B",
    "song_name": "Sorry Not Sorry"
  },
  {
    "artist": "K. Michelle",
    "genre": "R&B",
    "song_name": "Not a Little Bit"
  },
  {
    "artist": "Young M.A",
    "genre": "R&B",
    "song_name": "OOOUUU"
  },
  {
    "artist": "Kehlani",
    "genre": "R&B",
    "song_name": "CRZY"
  },
  {
    "artist": "Bryson Tiller",
    "genre": "R&B",
    "song_name": "Exchange"
  },
  {
    "artist": "Rae Sremmurd",
    "genre": "R&B",
    "song_name": "Look Alive ft. Drake"
  },
  {
    "artist": "ZAYN",
    "genre": "R&B",
    "song_name": "Pillowtalk"
  },
  {
    "artist": "SZA",
    "genre": "R&B",
    "song_name": "Love Galore ft. Travis Scott"
  },
  {
    "artist": "Khalid",
    "genre": "R&B",
    "song_name": "Location"
  },
  {
    "artist": "Daniel Caesar",
    "genre": "R&B",
    "song_name": "Get You ft. Kali Uchis"
  },
  {
    "artist": "Bruno Mars",
    "genre": "R&B",
    "song_name": "That's What I Like"
  },
  {
    "artist": "Childish Gambino",
    "genre": "R&B",
    "song_name": "Redbone"
  },
  {
    "artist": "Jhené Aiko",
    "genre": "R&B",
    "song_name": "While We're Young"
  },
  {
    "artist": "The Weeknd",
    "genre": "R&B",
    "song_name": "Starboy ft. Daft Punk"
  },
  {
    "artist": "Bryson Tiller",
    "genre": "R&B",
    "song_name": "Run Me Dry"
  },
  {
    "artist": "Kehlani",
    "genre": "R&B",
    "song_name": "Distraction"
  },
  {
    "artist": "SZA",
    "genre": "R&B",
    "song_name": "The Weekend"
  },
  {
    "artist": "Tank",
    "genre": "R&B",
    "song_name": "When We"
  },
  {
    "artist": "Kendrick Lamar",
    "genre": "R&B",
    "song_name": "LOVE. ft. Zacari"
  },
  {
    "artist": "Jorja Smith",
    "genre": "R&B",
    "song_name": "On My Mind ft. Preditah"
  },
  {
    "artist": "DJ Khaled",
    "genre": "R&B",
    "song_name": "Wild Thoughts ft. Rihanna, Bryson Tiller"
  },
  {
    "artist": "Miguel",
    "genre": "R&B",
    "song_name": "Sky Walker ft. Travis Scott"
  },
  {
    "artist": "Khalid",
    "genre": "R&B",
    "song_name": "Young Dumb & Broke"
  },
  {
    "artist": "SZA",
    "genre": "R&B",
    "song_name": "Drew Barrymore"
  },
  {
    "artist": "Kehlani",
    "genre": "R&B",
    "song_name": "CRZY"
  },
  {
    "artist": "6LACK",
    "genre": "R&B",
    "song_name": "Prblms"
  },
  {
    "artist": "Bruno Mars",
    "genre": "R&B",
    "song_name": "Versace On The Floor"
  },
  {
    "artist": "Jhené Aiko",
    "genre": "R&B",
    "song_name": "Maniac"
  },
  {
    "artist": "Miguel",
    "genre": "R&B",
    "song_name": "Told You So"
  },
  {
    "artist": "Bryson Tiller",
    "genre": "R&B",
    "song_name": "Don't"
  },
  {
    "artist": "Daniel Caesar",
    "genre": "R&B",
    "song_name": "Blessed"
  },
  {
    "artist": "Rihanna",
    "genre": "R&B",
    "song_name": "Love On The Brain"
  },
  {
    "artist": "Khalid",
    "genre": "R&B",
    "song_name": "Saved"
  },
  {
    "artist": "SZA",
    "genre": "R&B",
    "song_name": "Garden (Say It Like Dat)"
  },
  {
    "artist": "Bruno Mars",
    "genre": "R&B",
    "song_name": "24K Magic"
  },
  {
    "artist": "Jhené Aiko",
    "genre": "R&B",
    "song_name": "Frequency"
  },
  {
    "artist": "Khalid",
    "genre": "R&B",
    "song_name": "Coaster"
  },
  {
    "artist": "Solange",
    "genre": "R&B",
    "song_name": "Cranes in the Sky"
  },
  {
    "artist": "Childish Gambino",
    "genre": "R&B",
    "song_name": "Me and Your Mama"
  },
  {
    "artist": "Kehlani",
    "genre": "R&B",
    "song_name": "Advice"
  },
  {
    "artist": "SZA",
    "genre": "R&B",
    "song_name": "Supermodel"
  },
  {
    "artist": "Kendrick Lamar",
    "genre": "R&B",
    "song_name": "HUMBLE."
  },
  {
    "artist": "Bryson Tiller",
    "genre": "R&B",
    "song_name": "Exchange"
  },
  {
    "artist": "Daniel Caesar",
    "genre": "R&B",
    "song_name": "We Find Love"
  },
  {
    "artist": "Jhené Aiko",
    "genre": "R&B",
    "song_name": "Sativa ft. Swae Lee"
  },
  {
    "artist": "The Weeknd",
    "genre": "R&B",
    "song_name": "I Feel It Coming ft. Daft Punk"
  },
  {
    "artist": "Miguel",
    "genre": "R&B",
    "song_name": "Come Through and Chill ft. J. Cole"
  },
  {
    "artist": "Khalid",
    "genre": "R&B",
    "song_name": "Let's Go"
  },
  {
    "artist": "SZA",
    "genre": "R&B",
    "song_name": "Broken Clocks"
  },
  {
    "artist": "Bruno Mars",
    "genre": "R&B",
    "song_name": "Chunky"
  },
  {
    "artist": "Tank",
    "genre": "R&B",
    "song_name": "F***in Wit Me"
  },
  {
    "artist": "Kehlani",
    "genre": "R&B",
    "song_name": "Keep On"
  },
  {
    "artist": "Jhené Aiko",
    "genre": "R&B",
    "song_name": "First Fuck ft. 6LACK"
  },
  {
    "artist": "Miguel",
    "genre": "R&B",
    "song_name": "Banana Clip"
  },
  {
    "artist": "Ella Mai",
    "genre": "R&B",
    "song_name": "Boo'd Up"
  },
  {
    "artist": "Childish Gambino",
    "genre": "R&B",
    "song_name": "This Is America"
  },
  {
    "artist": "Drake",
    "genre": "R&B",
    "song_name": "In My Feelings"
  },
  {
    "artist": "H.E.R.",
    "genre": "R&B",
    "song_name": "Focus"
  },
  {
    "artist": "Khalid",
    "genre": "R&B",
    "song_name": "Better"
  },
  {
    "artist": "SZA",
    "genre": "R&B",
    "song_name": "The Weekend"
  },
  {
    "artist": "Bruno Mars, Cardi B",
    "genre": "R&B",
    "song_name": "Finesse (Remix)"
  },
  {
    "artist": "The Carters",
    "genre": "R&B",
    "song_name": "APES**T"
  },
  {
    "artist": "Ella Mai",
    "genre": "R&B",
    "song_name": "Trip"
  },
  {
    "artist": "Khalid, Normani",
    "genre": "R&B",
    "song_name": "Love Lies"
  },
  {
    "artist": "Cardi B, Bad Bunny, J Balvin",
    "genre": "R&B",
    "song_name": "I Like It"
  },
  {
    "artist": "Toni Braxton",
    "genre": "R&B",
    "song_name": "Long As I Live"
  },
  {
    "artist": "6LACK, J. Cole",
    "genre": "R&B",
    "song_name": "Pretty Little Fears"
  },
  {
    "artist": "Miguel, J. Cole, Salaam Remi",
    "genre": "R&B",
    "song_name": "Come Through and Chill"
  },
  {
    "artist": "Queen Naija",
    "genre": "R&B",
    "song_name": "Medicine"
  },
  {
    "artist": "Ella Mai",
    "genre": "R&B",
    "song_name": "Shot Clock"
  },
  {
    "artist": "Khalid",
    "genre": "R&B",
    "song_name": "Talk"
  },
  {
    "artist": "Janelle Monáe",
    "genre": "R&B",
    "song_name": "Make Me Feel"
  },
  {
    "artist": "SZA",
    "genre": "R&B",
    "song_name": "Broken Clocks"
  },
  {
    "artist": "Daniel Caesar, H.E.R.",
    "genre": "R&B",
    "song_name": "Best Part"
  },
  {
    "artist": "Beyoncé, JAY-Z",
    "genre": "R&B",
    "song_name": "Summer"
  },
  {
    "artist": "Kali Uchis, Tyler, The Creator, Bootsy Collins",
    "genre": "R&B",
    "song_name": "After The Storm"
  },
  {
    "artist": "The Weeknd, Kendrick Lamar",
    "genre": "R&B",
    "song_name": "Pray For Me"
  },
  {
    "artist": "SZA, Travis Scott",
    "genre": "R&B",
    "song_name": "Love Galore"
  },
  {
    "artist": "Jacquees",
    "genre": "R&B",
    "song_name": "B.E.D."
  },
  {
    "artist": "Jorja Smith",
    "genre": "R&B",
    "song_name": "Blue Lights"
  },
  {
    "artist": "Tank",
    "genre": "R&B",
    "song_name": "When We"
  },
  {
    "artist": "Miguel",
    "genre": "R&B",
    "song_name": "Sky Walker ft. Travis Scott"
  },
  {
    "artist": "SZA",
    "genre": "R&B",
    "song_name": "Garden (Say It Like Dat)"
  },
  {
    "artist": "Ella Mai",
    "genre": "R&B",
    "song_name": "Naked"
  },
  {
    "artist": "Jhené Aiko",
    "genre": "R&B",
    "song_name": "While We're Young"
  },
  {
    "artist": "Ne-Yo, Bebe Rexha, Stefflon Don",
    "genre": "R&B",
    "song_name": "Push Back"
  },
  {
    "artist": "Rita Ora, Cardi B, Bebe Rexha, Charli XCX",
    "genre": "R&B",
    "song_name": "Girls"
  },
  {
    "artist": "Miguel",
    "genre": "R&B",
    "song_name": "Banana Clip"
  },
  {
    "artist": "Chris Brown",
    "genre": "R&B",
    "song_name": "Tempo"
  },
  {
    "artist": "H.E.R.",
    "genre": "R&B",
    "song_name": "Could've Been ft. Bryson Tiller"
  },
  {
    "artist": "Tinashe, Offset",
    "genre": "R&B",
    "song_name": "No Drama"
  },
  {
    "artist": "Ella Mai",
    "genre": "R&B",
    "song_name": "Whatchamacallit ft. Chris Brown"
  },
  {
    "artist": "Toni Braxton",
    "genre": "R&B",
    "song_name": "Deadwood"
  },
  {
    "artist": "Usher, Zaytoven",
    "genre": "R&B",
    "song_name": "Peace Sign"
  },
  {
    "artist": "SZA",
    "genre": "R&B",
    "song_name": "Doves In The Wind ft. Kendrick Lamar"
  },
  {
    "artist": "Tamia",
    "genre": "R&B",
    "song_name": "Leave It Smokin'"
  },
  {
    "artist": "Ella Mai",
    "genre": "R&B",
    "song_name": "Anymore"
  },
  {
    "artist": "Janelle Monáe",
    "genre": "R&B",
    "song_name": "I Like That"
  },
  {
    "artist": "Khalid",
    "genre": "R&B",
    "song_name": "Location"
  },
  {
    "artist": "H.E.R.",
    "genre": "R&B",
    "song_name": "As I Am"
  },
  {
    "artist": "Ella Mai",
    "genre": "R&B",
    "song_name": "Dangerous"
  },
  {
    "artist": "SZA",
    "genre": "R&B",
    "song_name": "Go Gina"
  },
  {
    "artist": "Miguel",
    "genre": "R&B",
    "song_name": "Come Through and Chill ft. J. Cole, Salaam Remi"
  },
  {
    "artist": "Chris Brown",
    "genre": "R&B",
    "song_name": "No Guidance ft. Drake"
  },
  {
    "artist": "Ella Mai",
    "genre": "R&B",
    "song_name": "Shot Clock"
  },
  {
    "artist": "Khalid",
    "genre": "R&B",
    "song_name": "Talk"
  },
  {
    "artist": "Ari Lennox",
    "genre": "R&B",
    "song_name": "Shea Butter Baby ft. J. Cole"
  },
  {
    "artist": "Normani",
    "genre": "R&B",
    "song_name": "Motivation"
  },
  {
    "artist": "Summer Walker",
    "genre": "R&B",
    "song_name": "Playing Games"
  },
  {
    "artist": "Lizzo",
    "genre": "R&B",
    "song_name": "Truth Hurts"
  },
  {
    "artist": "H.E.R.",
    "genre": "R&B",
    "song_name": "Hard Place"
  },
  {
    "artist": "The Weeknd",
    "genre": "R&B",
    "song_name": "Blinding Lights"
  },
  {
    "artist": "Beyoncé",
    "genre": "R&B",
    "song_name": "Before I Let Go"
  },
  {
    "artist": "Daniel Caesar",
    "genre": "R&B",
    "song_name": "Best Part ft. H.E.R."
  },
  {
    "artist": "SZA, Justin Timberlake",
    "genre": "R&B",
    "song_name": "The Other Side"
  },
  {
    "artist": "Lizzo",
    "genre": "R&B",
    "song_name": "Good as Hell"
  },
  {
    "artist": "Khalid",
    "genre": "R&B",
    "song_name": "Better"
  },
  {
    "artist": "Summer Walker",
    "genre": "R&B",
    "song_name": "Girls Need Love ft. Drake"
  },
  {
    "artist": "Ariana Grande",
    "genre": "R&B",
    "song_name": "Thank U, Next"
  },
  {
    "artist": "Normani, Sam Smith",
    "genre": "R&B",
    "song_name": "Dancing With A Stranger"
  },
  {
    "artist": "Chris Brown",
    "genre": "R&B",
    "song_name": "Undecided"
  },
  {
    "artist": "H.E.R.",
    "genre": "R&B",
    "song_name": "Focus"
  },
  {
    "artist": "Ella Mai",
    "genre": "R&B",
    "song_name": "Boo'd Up"
  },
  {
    "artist": "Beyoncé",
    "genre": "R&B",
    "song_name": "Spirit"
  },
  {
    "artist": "Kehlani, Ty Dolla $ign",
    "genre": "R&B",
    "song_name": "Nights Like This"
  },
  {
    "artist": "SZA",
    "genre": "R&B",
    "song_name": "Good Days"
  },
  {
    "artist": "Ariana Grande, Social House",
    "genre": "R&B",
    "song_name": "Boyfriend"
  },
  {
    "artist": "Lucky Daye",
    "genre": "R&B",
    "song_name": "Roll Some Mo"
  },
  {
    "artist": "Summer Walker",
    "genre": "R&B",
    "song_name": "Come Thru ft. Usher"
  },
  {
    "artist": "Teyana Taylor, King Combs",
    "genre": "R&B",
    "song_name": "How You Want It?"
  },
  {
    "artist": "Chris Brown, Drake",
    "genre": "R&B",
    "song_name": "No Guidance"
  },
  {
    "artist": "Ari Lennox",
    "genre": "R&B",
    "song_name": "BMO"
  },
  {
    "artist": "H.E.R.",
    "genre": "R&B",
    "song_name": "Slide ft. YG"
  },
  {
    "artist": "Daniel Caesar, Brandy",
    "genre": "R&B",
    "song_name": "Love Again"
  },
  {
    "artist": "Khalid",
    "genre": "R&B",
    "song_name": "Right Back ft. A Boogie Wit Da Hoodie"
  },
  {
    "artist": "Normani",
    "genre": "R&B",
    "song_name": "Waves ft. 6LACK"
  },
  {
    "artist": "Summer Walker",
    "genre": "R&B",
    "song_name": "Body"
  },
  {
    "artist": "Ella Mai",
    "genre": "R&B",
    "song_name": "Whatchamacallit ft. Chris Brown"
  },
  {
    "artist": "The Weeknd",
    "genre": "R&B",
    "song_name": "Heartless"
  },
  {
    "artist": "Beyoncé, Shatta Wale, Major Lazer",
    "genre": "R&B",
    "song_name": "Already"
  },
  {
    "artist": "SZA, Travis Scott",
    "genre": "R&B",
    "song_name": "Love Galore"
  },
  {
    "artist": "Chris Brown, Gunna",
    "genre": "R&B",
    "song_name": "Heat"
  },
  {
    "artist": "Summer Walker",
    "genre": "R&B",
    "song_name": "Potential"
  },
  {
    "artist": "H.E.R.",
    "genre": "R&B",
    "song_name": "Could've Been ft. Bryson Tiller"
  },
  {
    "artist": "Ari Lennox",
    "genre": "R&B",
    "song_name": "Chicago Boy"
  },
  {
    "artist": "Normani",
    "genre": "R&B",
    "song_name": "Kordei Waves ft. 6LACK"
  },
  {
    "artist": "Khalid",
    "genre": "R&B",
    "song_name": "Free Spirit"
  },
  {
    "artist": "Ella Mai",
    "genre": "R&B",
    "song_name": "Gut Feeling ft. H.E.R."
  },
  {
    "artist": "Lizzo",
    "genre": "R&B",
    "song_name": "Tempo ft. Missy Elliott"
  },
  {
    "artist": "The Weeknd",
    "genre": "R&B",
    "song_name": "Save Your Tears"
  },
  {
    "artist": "The Weeknd",
    "genre": "R&B",
    "song_name": "Blinding Lights"
  },
  {
    "artist": "Chris Brown, Young Thug",
    "genre": "R&B",
    "song_name": "Go Crazy"
  },
  {
    "artist": "Jhene Aiko",
    "genre": "R&B",
    "song_name": "P*$$Y Fairy (OTW)"
  },
  {
    "artist": "PARTYNEXTDOOR, Rihanna",
    "genre": "R&B",
    "song_name": "Believe It"
  },
  {
    "artist": "Roddy Ricch",
    "genre": "R&B",
    "song_name": "High Fashion ft. Mustard"
  },
  {
    "artist": "Summer Walker, Usher",
    "genre": "R&B",
    "song_name": "Come Thru"
  },
  {
    "artist": "Megan Thee Stallion, Beyonce",
    "genre": "R&B",
    "song_name": "Savage (Remix)"
  },
  {
    "artist": "SZA, Ty Dolla $ign",
    "genre": "R&B",
    "song_name": "Hit Different"
  },
  {
    "artist": "The Weeknd",
    "genre": "R&B",
    "song_name": "Heartless"
  },
  {
    "artist": "HER",
    "genre": "R&B",
    "song_name": "Damage"
  },
  {
    "artist": "Bryson Tiller",
    "genre": "R&B",
    "song_name": "Outta Time ft. Drake"
  },
  {
    "artist": "Jhené Aiko, H.E.R.",
    "genre": "R&B",
    "song_name": "B.S."
  },
  {
    "artist": "Kehlani",
    "genre": "R&B",
    "song_name": "Can I ft. Tory Lanez"
  },
  {
    "artist": "Teyana Taylor, IMAN",
    "genre": "R&B",
    "song_name": "Wake Up Love"
  },
  {
    "artist": "dvsn, Snoh Aalegra",
    "genre": "R&B",
    "song_name": "Between Us"
  },
  {
    "artist": "Chloe x Halle",
    "genre": "R&B",
    "song_name": "Do It"
  },
  {
    "artist": "John Legend",
    "genre": "R&B",
    "song_name": "Conversations in the Dark"
  },
  {
    "artist": "Joji",
    "genre": "R&B",
    "song_name": "Run"
  },
  {
    "artist": "Tory Lanez",
    "genre": "R&B",
    "song_name": "Do The Most"
  },
  {
    "artist": "Alicia Keys",
    "genre": "R&B",
    "song_name": "Underdog"
  },
  {
    "artist": "Lil Baby",
    "genre": "R&B",
    "song_name": "Emotionally Scarred"
  },
  {
    "artist": "Ari Lennox",
    "genre": "R&B",
    "song_name": "BUSSIT"
  },
  {
    "artist": "Lucky Daye, Ty Dolla $ign, Wale",
    "genre": "R&B",
    "song_name": "Roll Some Mo (Remix)"
  },
  {
    "artist": "Trey Songz",
    "genre": "R&B",
    "song_name": "Back Home ft. Summer Walker"
  },
  {
    "artist": "SZA",
    "genre": "R&B",
    "song_name": "Good Days"
  },
  {
    "artist": "Giveon",
    "genre": "R&B",
    "song_name": "Heartbreak Anniversary"
  },
  {
    "artist": "Beyoncé",
    "genre": "R&B",
    "song_name": "Black Parade"
  },
  {
    "artist": "Queen Naija",
    "genre": "R&B",
    "song_name": "Butterflies Pt. 2"
  },
  {
    "artist": "Jazmine Sullivan",
    "genre": "R&B",
    "song_name": "Lost One"
  },
  {
    "artist": "Brent Faiyaz",
    "genre": "R&B",
    "song_name": "Dead Man Walking"
  },
  {
    "artist": "Miguel",
    "genre": "R&B",
    "song_name": "Funeral"
  },
  {
    "artist": "Summer Walker",
    "genre": "R&B",
    "song_name": "Body"
  },
  {
    "artist": "Kiana Ledé",
    "genre": "R&B",
    "song_name": "Mad At Me."
  },
  {
    "artist": "Alicia Keys",
    "genre": "R&B",
    "song_name": "So Done ft. Khalid"
  },
  {
    "artist": "Ella Mai",
    "genre": "R&B",
    "song_name": "Not Another Love Song"
  },
  {
    "artist": "Tory Lanez",
    "genre": "R&B",
    "song_name": "The Take ft. Chris Brown"
  },
  {
    "artist": "dvsn",
    "genre": "R&B",
    "song_name": "A Muse"
  },
  {
    "artist": "Lianne La Havas",
    "genre": "R&B",
    "song_name": "Can't Fight"
  },
  {
    "artist": "Giveon",
    "genre": "R&B",
    "song_name": "LIKE I WANT YOU"
  },
  {
    "artist": "JoJo",
    "genre": "R&B",
    "song_name": "Man"
  },
  {
    "artist": "Usher",
    "genre": "R&B",
    "song_name": "Bad Habits"
  },
  {
    "artist": "Trey Songz",
    "genre": "R&B",
    "song_name": "Circles"
  },
  {
    "artist": "Ari Lennox",
    "genre": "R&B",
    "song_name": "Speak To Me"
  },
  {
    "artist": "dvsn",
    "genre": "R&B",
    "song_name": "Miss Me?"
  },
  {
    "artist": "Brandy",
    "genre": "R&B",
    "song_name": "Baby Mama ft. Chance The Rapper"
  },
  {
    "artist": "Silk Sonic (Bruno Mars, Anderson .Paak)",
    "genre": "R&B",
    "song_name": "Leave The Door Open"
  },
  {
    "artist": "Jazmine Sullivan",
    "genre": "R&B",
    "song_name": "Pick Up Your Feelings"
  },
  {
    "artist": "Giveon",
    "genre": "R&B",
    "song_name": "Heartbreak Anniversary"
  },
  {
    "artist": "Chris Brown, Young Thug",
    "genre": "R&B",
    "song_name": "Go Crazy"
  },
  {
    "artist": "Doja Cat",
    "genre": "R&B",
    "song_name": "Kiss Me More ft. SZA"
  },
  {
    "artist": "H.E.R.",
    "genre": "R&B",
    "song_name": "Damage"
  },
  {
    "artist": "Jhené Aiko",
    "genre": "R&B",
    "song_name": "Lead The Way"
  },
  {
    "artist": "Miguel",
    "genre": "R&B",
    "song_name": "Art Dealer Chic 4"
  },
  {
    "artist": "Majid Jordan",
    "genre": "R&B",
    "song_name": "Waves of Blue"
  },
  {
    "artist": "Ella Mai",
    "genre": "R&B",
    "song_name": "Not Another Love Song"
  },
  {
    "artist": "Bruno Mars, Anderson .Paak, Silk Sonic",
    "genre": "R&B",
    "song_name": "Skate"
  },
  {
    "artist": "Arlo Parks",
    "genre": "R&B",
    "song_name": "Hurt"
  },
  {
    "artist": "SZA",
    "genre": "R&B",
    "song_name": "Good Days"
  },
  {
    "artist": "Giveon",
    "genre": "R&B",
    "song_name": "Like I Want You"
  },
  {
    "artist": "Tiana Major9",
    "genre": "R&B",
      "song_name": "Same Space?"
  },
  {
    "artist": "Lucky Daye",
    "genre": "R&B",
    "song_name": "How Much Can A Heart Take ft. YEBBA"
  },
  {
    "artist": "Victoria Monét",
    "genre": "R&B",
    "song_name": "Coastin'"
  },
  {
    "artist": "Brent Faiyaz",
    "genre": "R&B",
    "song_name": "Gravity ft. Tyler, The Creator"
  },
  {
    "artist": "Doja Cat",
    "genre": "R&B",
    "song_name": "Need to Know"
  },
  {
    "artist": "Blxst, Ty Dolla $ign, Tyga",
    "genre": "R&B",
    "song_name": "Chosen ft. Ty Dolla $ign, Tyga"
  },
  {
    "artist": "Jorja Smith",
    "genre": "R&B",
    "song_name": "Addicted"
  },
  {
    "artist": "Tinashe, Buddy",
    "genre": "R&B",
    "song_name": "Pasadena"
  },
  {
    "artist": "Fousheé",
    "genre": "R&B",
    "song_name": "gold fronts"
  },
  {
    "artist": "Bryson Tiller",
    "genre": "R&B",
    "song_name": "Sorrows"
  },
  {
    "artist": "Teyana Taylor, Davido",
    "genre": "R&B",
    "song_name": "Killa"
  },
  {
    "artist": "Lucky Daye, YEBBA",
    "genre": "R&B",
    "song_name": "How Much Can A Heart Take"
  },
  {
    "artist": "Mary J. Blige",
    "genre": "R&B",
    "song_name": "Good Morning Gorgeous"
  },
  {
    "artist": "Joyce Wrice, Freddie Gibbs",
    "genre": "R&B",
    "song_name": "On One"
  },
  {
    "artist": "HER",
    "genre": "R&B",
    "song_name": "Come Through ft. Chris Brown"
  },
  {
    "artist": "Miguel",
    "genre": "R&B",
    "song_name": "Funeral"
  },
  {
    "artist": "Yebba",
    "genre": "R&B",
    "song_name": "Boomerang ft. A$AP Rocky"
  },
  {
    "artist": "Ella Mai",
    "genre": "R&B",
    "song_name": "Shot Clock"
  },
  {
    "artist": "Blxst, Tyga, Ty Dolla $ign",
    "genre": "R&B",
    "song_name": "Chosen ft. Ty Dolla $ign, Tyga"
  },
  {
    "artist": "Mariah the Scientist",
    "genre": "R&B",
    "song_name": "2 You"
  },
  {
    "artist": "Fousheé",
    "genre": "R&B",
    "song_name": "single af"
  },
  {
    "artist": "Tone Stith",
    "genre": "R&B",
    "song_name": "Devotion"
  },
  {
    "artist": "Miguel",
    "genre": "R&B",
    "song_name": "Funeral"
  },
  {
    "artist": "Kehlani, Keyshia Cole",
    "genre": "R&B",
    "song_name": "All Me ft. Keyshia Cole"
  },
  {
    "artist": "GIVEON",
    "genre": "R&B",
    "song_name": "FOR TONIGHT"
  },
  {
    "artist": "Pink Sweat$",
    "genre": "R&B",
    "song_name": "At My Worst ft. Kehlani"
  },
  {
    "artist": "Lucky Daye",
    "genre": "R&B",
    "song_name": "Over"
  },
  {
    "artist": "Teyana Taylor",
    "genre": "R&B",
    "song_name": "Concrete"
  },
  {
    "artist": "Queen Naija, Ari Lennox",
    "genre": "R&B",
    "song_name": "Set Him Up"
  },
  {
    "artist": "Leon Bridges",
    "genre": "R&B",
    "song_name": "Motorbike"
  },
  {
    "artist": "SZA",
    "genre": "R&B",
    "song_name": "I Hate U"
  },
  {
    "artist": "Giveon",
    "genre": "R&B",
    "song_name": "Stuck on You"
  },
  {
    "artist": "Snoh Aalegra",
    "genre": "R&B",
    "song_name": "Lost You"
  },
  {
    "artist": "Joyce Wrice",
    "genre": "R&B",
    "song_name": "Addicted"
  }
  
  
  
  
  
  
  
  
]
]